data/__init__.py
data/fleet.py
data/io.py
data/preprocess.py
features/__init__.py
features/feature_engineering.py
features/simulation.py
models/__init__.py
models/prediction_interval.py
models/train_model.py
kia_remarketing_supply-1.0.0.dist-info/METADATA
kia_remarketing_supply-1.0.0.dist-info/WHEEL
kia_remarketing_supply-1.0.0.dist-info/top_level.txt
kia_remarketing_supply-1.0.0.dist-info/RECORD
