Metadata-Version: 2.1
Name: kia-remarketing-supply
Version: 1.0.0
Summary: Custom modules for kia_remarketing_supply
Home-page: https://gitlab.autoeveramerica.com/jasonminsookim/kia_remarketing_supply
Author: Jason Kim
Author-email: jasonminsookim@gmail.com
License: UNKNOWN
Project-URL: Bug Tracker, https://gitlab.autoeveramerica.com/jasonminsookim/kia_remarketing_supply/-/issues
Platform: UNKNOWN
Classifier: Programming Language :: Python :: 3
Classifier: License :: OSI Approved :: MIT License
Classifier: Operating System :: OS Independent
Requires-Python: >=3.6
